CHANGES.rst
CODE_OF_CONDUCT.md
CONTRIBUTING.md
CONTRIBUTORS.rst
LICENSE
MANIFEST.in
README.rst
setup.cfg
setup.py
src/senaite/__init__.py
src/senaite.sync.egg-info/PKG-INFO
src/senaite.sync.egg-info/SOURCES.txt
src/senaite.sync.egg-info/dependency_links.txt
src/senaite.sync.egg-info/entry_points.txt
src/senaite.sync.egg-info/namespace_packages.txt
src/senaite.sync.egg-info/not-zip-safe
src/senaite.sync.egg-info/requires.txt
src/senaite.sync.egg-info/top_level.txt
src/senaite/sync/__init__.py
src/senaite/sync/config.py
src/senaite/sync/configure.zcml
src/senaite/sync/fetchstep.py
src/senaite/sync/fieldmanagers.py
src/senaite/sync/importstep.py
src/senaite/sync/setuphandlers.py
src/senaite/sync/souphandler.py
src/senaite/sync/syncerror.py
src/senaite/sync/syncstep.py
src/senaite/sync/updatestep.py
src/senaite/sync/utils.py
src/senaite/sync/browser/__init__.py
src/senaite/sync/browser/add.py
src/senaite/sync/browser/autosync.py
src/senaite/sync/browser/configure.zcml
src/senaite/sync/browser/interfaces.py
src/senaite/sync/browser/views.py
src/senaite/sync/browser/templates/add.pt
src/senaite/sync/browser/templates/content_types.pt
src/senaite/sync/browser/templates/sync.pt
src/senaite/sync/profiles/default/actions.xml
src/senaite/sync/profiles/default/metadata.xml
src/senaite/sync/profiles/default/senaite.sync.txt
src/senaite/sync/upgrade/__init__.py
src/senaite/sync/upgrade/configure.zcml
src/senaite/sync/upgrade/v01_00_000.py
src/senaite/sync/upgrade/v01_00_001.py