Metadata-Version: 1.1
Name: senaite.sync
Version: 1.0.1
Summary: SENAITE SYNC
Home-page: https://github.com/senaite/senaite.sync
Author: SENAITE Foundation
Author-email: hello@senaite.com
License: GPLv3
Platform: UNKNOWN
Classifier: Programming Language :: Python
Classifier: Framework :: Plone
Classifier: Framework :: Zope2
